{
  "en_es": {
    "embarazada": "pregnant (not embarrassed)",
    "sensible": "sensitive (not sensible)",
    "actualmente": "currently (not actually)",
    "asistir": "to attend (not to assist)",
    "bizarro": "dashing/brave (not bizarre)",
    "carpeta": "folder (not carpet)",
    "constipado": "to have a cold (not constipated)",
    "discutir": "to argue (not to discuss)",
    "en absoluto": "not at all (not absolutely)",
    "éxito": "success (not exit)",
    "fábrica": "factory (not fabric)",
    "grabar": "to record (not to grab)",
    "lectura": "reading (not lecture)",
    "molestar": "to bother (not to molest)",
    "noticia": "news (not notice)",
    "oficina": "office (not workshop)",
    "pretender": "to try (not to pretend)",
    "realizar": "to do/carry out (not to realize)",
    "recordar": "to remember (not to record)",
    "sopa": "soup (not soap)",
    "trampa": "trap/trick (not tramp)"
  },
  "en_fr": {
    "actuellement": "currently (not actually)",
    "assister": "to attend (not to assist)",
    "blesser": "to wound (not to bless)",
    "coin": "corner (not coin)",
    "déception": "disappointment (not deception)",
    "défendre": "to forbid (not to defend)",
    "demander": "to ask (not to demand)",
    "éditeur": "publisher (not editor)",
    "envy": "annoyance (not envy)",
    "gift": "poison (not gift)",
    "ignorer": "to not know (not to ignore)",
    "journée": "day (not journey)",
    "librairie": "bookstore (not library)",
    "monnaie": "change/currency (not money)",
    "pain": "bread (not pain)",
    "pièce": "room/coin (not piece)",
    "propre": "clean (not proper)",
    "sensible": "sensitive (not sensible)",
    "sympathique": "nice (not sympathetic)",
    "veste": "jacket (not vest)"
  },
  "en_de": {
    "aktuell": "current (not actual)",
    "also": "so/therefore (not also)",
    "bald": "soon (not bald)",
    "bekommen": "to receive (not to become)",
    "billig": "cheap (not bill)",
    "brav": "well-behaved (not brave)",
    "chef": "boss (not chef)",
    "eventuell": "possibly (not eventually)",
    "gift": "poison (not gift)",
    "handy": "mobile phone (not handy)",
    "hell": "bright (not hell)",
    "herb": "bitter/tart (not herb)",
    "mist": "manure (not mist)",
    "muffe": "sleeve/pipe (not muff)",
    "rat": "advice (not rat)",
    "sensibel": "sensitive (not sensible)",
    "stift": "pen (not gift)",
    "winken": "to wave (not to wink)"
  },
  "en_it": {
    "camera": "room (not camera)",
    "cantina": "wine cellar (not canteen)",
    "confetti": "sugared almonds (not confetti)",
    "estro": "inspiration (not estrogen)",
    "fattoria": "farm (not factory)",
    "firmare": "to sign (not to firm)",
    "grosso": "big (not gross)",
    "largo": "wide (not large)",
    "magazzino": "warehouse (not magazine)",
    "palazzo": "building (not palace)",
    "preservativo": "condom (not preservative)",
    "salire": "to go up (not to sail)",
    "seccatura": "nuisance (not secateurs)",
    "sensitivo": "sensitive (not sensitive to touch)",
    "simpatia": "likability (not sympathy)",
    "tassa": "tax (not cup)",
    "tenero": "tender (not tenuous)",
    "traffico": "traffic (not trafficking)"
  },
  "en_pt": {
    "apelido": "nickname (not surname)",
    "balcão": "counter (not balcony)",
    "brincar": "to play (not to blink)",
    "colester": "to glue (not to cluster)",
    "costume": "habit (not costume)",
    "esquisito": "strange (not exquisite)",
    "exquisito": "delicious (not exquisite)",
    "falso": "false (not false friend)",
    "fechar": "to close (not to fetch)",
    "gesso": "plaster (not gypsum)",
    "gosto": "taste (not cost)",
    "largo": "wide (not large)",
    "legenda": "subtitle (not legend)",
    "novela": "soap opera (not novel)",
    "oficina": "workshop (not office)",
    "palhaço": "clown (not palace)",
    "pasta": "folder (not pasta)",
    "polvo": "octopus (not powder)",
    "preservativo": "condom (not preservative)",
    "propaganda": "advertisement (not propaganda)",
    "reclamar": "to complain (not to claim)",
    "salsa": "parsley (not salsa)",
    "solo": "alone/soil (not solo)"
  },
  "en_nl": {
    "actueel": "current (not actual)",
    "dankbaar": "grateful (not dank)",
    "dun": "thin (not done)",
    "eventueel": "possibly (not eventually)",
    "formulier": "form (not formula)",
    "gek": "crazy (not geek)",
    "gift": "poison (not gift)",
    "groot": "big/great (not groot)",
    "hoor": "you know (not hooray)",
    "klant": "customer (not plant)",
    "laken": "sheet (not lake)",
    "lamp": "lamp (not lump)",
    "medicijn": "medicine (not medicine)",
    "mok": "mug (not mock)",
    "rook": "smoke (not rook)",
    "rookworst": "smoked sausage (not rook worst)",
    "schade": "damage (not shade)",
    "slim": "smart (not slim)",
    "straf": "punishment (not staff)",
    "vlek": "stain (not fleck)",
    "wandelen": "to walk (not to wander)",
    "winkel": "shop (not winkle)"
  },
  "en_sv": {
    "akt": "document (not act)",
    "artikel": "article (not artifact)",
    "begå": "to commit (not to beg)",
    "bra": "good (not bra)",
    "eventuell": "possible (not eventual)",
    "fabrik": "factory (not fabric)",
    "familj": "family (not familiar)",
    "gift": "poison/married (not gift)",
    "glas": "ice cream (not glass)",
    "känslig": "sensitive (not senseless)",
    "kon": "cone (not con)",
    "lek": "game (not leek)",
    "limpa": "loaf (not limp)",
    "låda": "box (not load)",
    "näring": "nutrition (not nearing)",
    "rolig": "funny (not roly)",
    "semester": "vacation (not semester)",
    "skön": "beautiful (not skunk)",
    "smal": "narrow (not small)",
    "syster": "sister (not system)",
    "tårta": "cake (not torte)",
    "välling": "porridge (not dwelling)"
  },
  "en_pl": {
    "aktualny": "current (not actual)",
    "asystent": "assistant (not existent)",
    "bydło": "cattle (not by dłoń)",
    "chemia": "chemistry (not chemo)",
    "długopis": "pen (not long nose)",
    "dodatek": "supplement (not additive)",
    "dywan": "carpet (not divan)",
    "ekran": "screen (not ekran)",
    "fakt": "fact (not faked)",
    "gaz": "gas (not gauze)",
    "herbata": "tea (not herbata)",
    "kawa": "coffee (not kawa)",
    "laska": "cane (not laska)",
    "lustro": "mirror (not lust)",
    "materac": "mattress (not material)",
    "nawet": "even (not navet)",
    "ordynacja": "prescription (not ordination)",
    "parówka": "frankfurter (not parówka)",
    "pianka": "foam (not piano)",
    "szafka": "cabinet (not shaft)",
    "talerz": "plate (not talerz)",
    "zakaz": "prohibition (not zakaz)"
  },
  "en_tr": {
    "akıl": "mind/intelligence (not axle)",
    "baba": "father (not baba)",
    "bal": "honey (not ball)",
    "dert": "trouble/pain (not dirt)",
    "entrika": "intrigue (not entree)",
    "fena": "bad/wicked (not fena)",
    "hava": "weather/air (not hava)",
    "hiç": "never/none (not hit)",
    "hukuk": "law (not hook)",
    "kibar": "polite (not kebab)",
    "kutu": "box (not kutu)",
    "laf": "word/speech (not laugh)",
    "masa": "table (not masa)",
    "moral": "morale (not moral)",
    "pil": "battery (not pill)",
    "puan": "point/score (not puan)",
    "rapor": "report (not rapor)",
    "renk": "color (not renk)",
    "sade": "plain (not sade)",
    "tatil": "vacation (not title)",
    "termik": "thermal (not termic)",
    "yasa": "law (not yasa)"
  },
  "en_ja": {
    "アポイント": "appointment (not a point)",
    "コンセント": "power outlet (not consent)",
    "サイン": "signature (not sign)",
    "ダウン": "down/flu (not down)",
    "バイト": "part-time job (not bite)",
    "パン": "bread (not pan)",
    "マンション": "apartment (not mansion)",
    "モーニング": "morning set meal (not morning)",
    "サービス": "discount/freebie (not service)",
    "スーパー": "supermarket (not super)",
    "ワンマン": "autocratic (not one man)",
    "オーダー": "order (not odour)",
    "カンニング": "cheating (not cunning)",
    "シャーペン": "mechanical pencil (not sharp pen)",
    "スタンド": "lampstand/gas station (not stand)",
    "トランプ": "playing cards (not trump)",
    "マジック": "magic marker (not magic)",
    "アイデア": "idea (not id ea)",
    "イメージ": "image (not imagine)",
    "エネルギー": "energy (not energy drink)"
  },
  "en_zh": {
    "结实": "sturdy/strong (not conclusion)",
    "勉强": "reluctant (not barely)",
    "地道": "genuine/authentic (not underground)",
    "方便": "convenient (not direction)",
    "告诉": "to tell (not to sue)",
    "东西": "thing (not east-west)",
    "黄瓜": "cucumber (not yellow melon)",
    "白菜": "Chinese cabbage (not white vegetable)",
    "热水": "hot water (not boiled water)",
    "手机": "mobile phone (not hand machine)",
    "火车": "train (not fire vehicle)",
    "汽车": "car (not gas vehicle)",
    "颜色": "color (not face color)",
    "时间": "time (not between hours)",
    "认识": "to know/recognize (not to recognize as)",
    "知道": "to know (not to know the way)",
    "意思": "meaning (not idea thought)",
    "问题": "problem/question (not question topic)",
    "天气": "weather (not day air)",
    "空气": "air (not empty air)"
  },
  "en_ko": {
    "고등학교": "high school (not high grade school)",
    "대학교": "university (not great school)",
    "소개": "introduction (not small dog)",
    "소식": "news (not small food)",
    "약속": "promise (not medicine)",
    "차": "car/tea (not cha)",
    "공부": "study (not empty part)",
    "방학": "vacation (not room study)",
    "시험": "exam (not try po)",
    "숙제": "homework (not lodging)",
    "점심": "lunch (not dot heart)",
    "아침": "morning (not ah chim)",
    "저녁": "evening (not jeo nyeok)",
    "선생님": "teacher (not before life)",
    "친구": "friend (not chin goo)",
    "가방": "bag (not ga bang)",
    "책상": "desk (not book table)",
    "의자": "chair (not uija)",
    "냉장고": "refrigerator (not cold storage)",
    "세탁기": "washing machine (not wash machine)"
  }
}
